{
  "openapi": "3.0.1",
  "info": {
    "title": "Gerenciamento Financeiro",
    "version": "1.0"
  },
  "paths": {
    "/api/Auth/login": {
      "post": {
        "tags": [
          "Auth"
        ],
        "requestBody": {
          "content": {
            "application/json": {
              "schema": {
                "$ref": "#/components/schemas/Login"
              }
            },
            "text/json": {
              "schema": {
                "$ref": "#/components/schemas/Login"
              }
            },
            "application/*+json": {
              "schema": {
                "$ref": "#/components/schemas/Login"
              }
            }
          }
        },
        "responses": {
          "200": {
            "description": "OK"
          }
        }
      }
    },
    "/api/Auth/register": {
      "post": {
        "tags": [
          "Auth"
        ],
        "requestBody": {
          "content": {
            "application/json": {
              "schema": {
                "$ref": "#/components/schemas/Usuarios"
              }
            },
            "text/json": {
              "schema": {
                "$ref": "#/components/schemas/Usuarios"
              }
            },
            "application/*+json": {
              "schema": {
                "$ref": "#/components/schemas/Usuarios"
              }
            }
          }
        },
        "responses": {
          "200": {
            "description": "OK"
          }
        }
      }
    },
    "/api/Categorias": {
      "get": {
        "tags": [
          "Categorias"
        ],
        "parameters": [
          {
            "name": "usuarioId",
            "in": "query",
            "schema": {
              "type": "integer",
              "format": "int32"
            }
          }
        ],
        "responses": {
          "200": {
            "description": "OK"
          }
        }
      },
      "post": {
        "tags": [
          "Categorias"
        ],
        "parameters": [
          {
            "name": "usuarioId",
            "in": "query",
            "schema": {
              "type": "integer",
              "format": "int32"
            }
          }
        ],
        "requestBody": {
          "content": {
            "application/json": {
              "schema": {
                "$ref": "#/components/schemas/Categorias"
              }
            },
            "text/json": {
              "schema": {
                "$ref": "#/components/schemas/Categorias"
              }
            },
            "application/*+json": {
              "schema": {
                "$ref": "#/components/schemas/Categorias"
              }
            }
          }
        },
        "responses": {
          "200": {
            "description": "OK"
          }
        }
      },
      "put": {
        "tags": [
          "Categorias"
        ],
        "parameters": [
          {
            "name": "id",
            "in": "query",
            "schema": {
              "type": "integer",
              "format": "int32"
            }
          },
          {
            "name": "categoriaAtualizada",
            "in": "query",
            "schema": {
              "type": "string"
            }
          },
          {
            "name": "usuarioId",
            "in": "query",
            "schema": {
              "type": "integer",
              "format": "int32"
            }
          }
        ],
        "responses": {
          "200": {
            "description": "OK"
          }
        }
      }
    },
    "/api/Categorias/{id}": {
      "get": {
        "tags": [
          "Categorias"
        ],
        "parameters": [
          {
            "name": "id",
            "in": "path",
            "required": true,
            "schema": {
              "type": "integer",
              "format": "int32"
            }
          },
          {
            "name": "usuarioId",
            "in": "query",
            "schema": {
              "type": "integer",
              "format": "int32"
            }
          }
        ],
        "responses": {
          "200": {
            "description": "OK"
          }
        }
      },
      "delete": {
        "tags": [
          "Categorias"
        ],
        "parameters": [
          {
            "name": "id",
            "in": "path",
            "required": true,
            "schema": {
              "type": "integer",
              "format": "int32"
            }
          },
          {
            "name": "usuarioId",
            "in": "query",
            "schema": {
              "type": "integer",
              "format": "int32"
            }
          }
        ],
        "responses": {
          "200": {
            "description": "OK"
          }
        }
      }
    },
    "/api/Lancamentos/lancamento/{id}": {
      "get": {
        "tags": [
          "Lancamentos"
        ],
        "parameters": [
          {
            "name": "usuarioId",
            "in": "query",
            "schema": {
              "type": "integer",
              "format": "int32"
            }
          },
          {
            "name": "id",
            "in": "path",
            "required": true,
            "schema": {
              "type": "string"
            }
          }
        ],
        "responses": {
          "200": {
            "description": "OK"
          }
        }
      }
    },
    "/api/Lancamentos/{id}": {
      "get": {
        "tags": [
          "Lancamentos"
        ],
        "parameters": [
          {
            "name": "id",
            "in": "path",
            "required": true,
            "schema": {
              "type": "integer",
              "format": "int32"
            }
          },
          {
            "name": "usuarioId",
            "in": "query",
            "schema": {
              "type": "integer",
              "format": "int32"
            }
          }
        ],
        "responses": {
          "200": {
            "description": "OK"
          }
        }
      }
    },
    "/api/Lancamentos": {
      "post": {
        "tags": [
          "Lancamentos"
        ],
        "parameters": [
          {
            "name": "usuarioId",
            "in": "query",
            "schema": {
              "type": "integer",
              "format": "int32"
            }
          }
        ],
        "requestBody": {
          "content": {
            "application/json": {
              "schema": {
                "$ref": "#/components/schemas/Lancamentos"
              }
            },
            "text/json": {
              "schema": {
                "$ref": "#/components/schemas/Lancamentos"
              }
            },
            "application/*+json": {
              "schema": {
                "$ref": "#/components/schemas/Lancamentos"
              }
            }
          }
        },
        "responses": {
          "200": {
            "description": "OK",
            "content": {
              "text/plain": {
                "schema": {
                  "$ref": "#/components/schemas/Lancamentos"
                }
              },
              "application/json": {
                "schema": {
                  "$ref": "#/components/schemas/Lancamentos"
                }
              },
              "text/json": {
                "schema": {
                  "$ref": "#/components/schemas/Lancamentos"
                }
              }
            }
          }
        }
      },
      "put": {
        "tags": [
          "Lancamentos"
        ],
        "parameters": [
          {
            "name": "id",
            "in": "query",
            "schema": {
              "type": "integer",
              "format": "int32"
            }
          },
          {
            "name": "usuarioId",
            "in": "query",
            "schema": {
              "type": "integer",
              "format": "int32"
            }
          }
        ],
        "requestBody": {
          "content": {
            "application/json": {
              "schema": {
                "$ref": "#/components/schemas/Lancamentos"
              }
            },
            "text/json": {
              "schema": {
                "$ref": "#/components/schemas/Lancamentos"
              }
            },
            "application/*+json": {
              "schema": {
                "$ref": "#/components/schemas/Lancamentos"
              }
            }
          }
        },
        "responses": {
          "200": {
            "description": "OK"
          }
        }
      },
      "delete": {
        "tags": [
          "Lancamentos"
        ],
        "parameters": [
          {
            "name": "id",
            "in": "query",
            "schema": {
              "type": "integer",
              "format": "int32"
            }
          },
          {
            "name": "usuarioId",
            "in": "query",
            "schema": {
              "type": "integer",
              "format": "int32"
            }
          }
        ],
        "responses": {
          "200": {
            "description": "OK"
          }
        }
      }
    },
    "/api/Usuarios/id/{id}": {
      "get": {
        "tags": [
          "Usuarios"
        ],
        "parameters": [
          {
            "name": "id",
            "in": "path",
            "required": true,
            "schema": {
              "type": "integer",
              "format": "int32"
            }
          }
        ],
        "responses": {
          "200": {
            "description": "OK"
          }
        }
      }
    },
    "/api/Usuarios/nome/{nome}": {
      "get": {
        "tags": [
          "Usuarios"
        ],
        "parameters": [
          {
            "name": "nome",
            "in": "path",
            "required": true,
            "schema": {
              "type": "string"
            }
          }
        ],
        "responses": {
          "200": {
            "description": "OK"
          }
        }
      }
    },
    "/api/Usuarios": {
      "post": {
        "tags": [
          "Usuarios"
        ],
        "requestBody": {
          "content": {
            "application/json": {
              "schema": {
                "$ref": "#/components/schemas/Usuarios"
              }
            },
            "text/json": {
              "schema": {
                "$ref": "#/components/schemas/Usuarios"
              }
            },
            "application/*+json": {
              "schema": {
                "$ref": "#/components/schemas/Usuarios"
              }
            }
          }
        },
        "responses": {
          "200": {
            "description": "OK"
          }
        }
      },
      "get": {
        "tags": [
          "Usuarios"
        ],
        "responses": {
          "200": {
            "description": "OK"
          }
        }
      }
    },
    "/api/Usuarios/{usuarioId}": {
      "delete": {
        "tags": [
          "Usuarios"
        ],
        "parameters": [
          {
            "name": "usuarioId",
            "in": "path",
            "required": true,
            "schema": {
              "type": "integer",
              "format": "int32"
            }
          }
        ],
        "responses": {
          "200": {
            "description": "OK"
          }
        }
      }
    },
    "/api/Usuarios/NomeExiste/{nome}": {
      "get": {
        "tags": [
          "Usuarios"
        ],
        "parameters": [
          {
            "name": "nome",
            "in": "path",
            "required": true,
            "schema": {
              "type": "string"
            }
          }
        ],
        "responses": {
          "200": {
            "description": "OK"
          }
        }
      }
    }
  },
  "components": {
    "schemas": {
      "Categorias": {
        "required": [
          "nome",
          "usuarioId"
        ],
        "type": "object",
        "properties": {
          "id": {
            "type": "integer",
            "format": "int32"
          },
          "nome": {
            "minLength": 1,
            "type": "string"
          },
          "usuarioId": {
            "type": "integer",
            "format": "int32"
          }
        },
        "additionalProperties": false
      },
      "Lancamentos": {
        "required": [
          "categoriaId",
          "data",
          "tipo",
          "usuarioId",
          "valor"
        ],
        "type": "object",
        "properties": {
          "id": {
            "type": "integer",
            "format": "int32"
          },
          "valor": {
            "type": "number",
            "format": "double"
          },
          "valorGlobal": {
            "type": "string",
            "nullable": true
          },
          "tipo": {
            "minLength": 1,
            "type": "string"
          },
          "usuarioId": {
            "type": "integer",
            "format": "int32"
          },
          "categoriaId": {
            "type": "integer",
            "format": "int32"
          },
          "data": {
            "type": "string",
            "format": "date-time"
          }
        },
        "additionalProperties": false
      },
      "Login": {
        "required": [
          "nomeUsuario",
          "senha"
        ],
        "type": "object",
        "properties": {
          "nomeUsuario": {
            "minLength": 1,
            "type": "string"
          },
          "senha": {
            "minLength": 1,
            "type": "string"
          }
        },
        "additionalProperties": false
      },
      "Usuarios": {
        "required": [
          "nome",
          "nomeUsuario",
          "senha"
        ],
        "type": "object",
        "properties": {
          "id": {
            "type": "integer",
            "format": "int32"
          },
          "nome": {
            "minLength": 1,
            "type": "string"
          },
          "nomeUsuario": {
            "minLength": 1,
            "type": "string"
          },
          "senha": {
            "minLength": 1,
            "type": "string"
          }
        },
        "additionalProperties": false
      }
    }
  }
}